pysimpletree/__init__.py
pysimpletree/binarytree.py
pysimpletree-1.1.5.dist-info/LICENSE.txt
pysimpletree-1.1.5.dist-info/WHEEL
pysimpletree-1.1.5.dist-info/METADATA
pysimpletree-1.1.5.dist-info/RECORD
